[
    {
      "id": 1,
      "image": "https://www.menutiger.com/_next/image?url=%2F_next%2Fstatic%2Fmedia%2Fpartner_2.93038ea5.webp&w=3840&q=75",
      "alt": "Alkauser Delhi"
    },
    {
      "id": 2,
      "image": "https://www.menutiger.com/_next/image?url=%2F_next%2Fstatic%2Fmedia%2Fpartner_3.86e2040d.webp&w=3840&q=75",
      "alt": "Arsalan"
    },
    {
      "id": 3,
      "image": "https://www.menutiger.com/_next/image?url=%2F_next%2Fstatic%2Fmedia%2Fpartner_4.3229abf4.webp&w=2048&q=75",
      "alt": "Basket Robbins"
    },
    {
      "id": 4,
      "image": "https://www.menutiger.com/_next/image?url=%2F_next%2Fstatic%2Fmedia%2Fpartner_6.759b378d.webp&w=3840&q=75",
      "alt": "Costa Coffee"
    },
    {
      "id": 5,
      "image": "https://www.menutiger.com/_next/image?url=%2F_next%2Fstatic%2Fmedia%2Fpartner_3.86e2040d.webp&w=3840&q=75",
      "alt": "Hardees"
    },
    {
      "id": 6,
      "image": "https://www.menutiger.com/_next/image?url=%2F_next%2Fstatic%2Fmedia%2Fpartner_5.9ae32338.webp&w=3840&q=75",
      "alt": "KFC"
    },
    {
      "id": 7,
      "image": "https://www.menutiger.com/_next/image?url=%2F_next%2Fstatic%2Fmedia%2Fpartner_1.7faf492e.webp&w=3840&q=75",
      "alt": "Krispy Kreme"
    },
    {
      "id": 8,
      "image": "https://encrypted-tbn0.gstatic.com/images?q=tbn:ANd9GcTlP5rNIY8exGUtKwDqTmuKkJsRMy5cAhjqOA&s",
      "alt": "Roadhouse cafe"
    },
    {
      "id": 9,
      "image": "https://www.menutiger.com/_next/image?url=%2F_next%2Fstatic%2Fmedia%2Fpartner_5.9ae32338.webp&w=3840&q=75",
      "alt": "TGI Fridays"
    },
    {
      "id": 10,
      "image": "https://www.menutiger.com/_next/image?url=%2F_next%2Fstatic%2Fmedia%2Fpartner_5.9ae32338.webp&w=3840&q=75",
      "alt": "Pramod Laddu"
    },
    {
      "id": 11,
      "image": "https://www.menutiger.com/_next/image?url=%2F_next%2Fstatic%2Fmedia%2Fpartner_5.9ae32338.webp&w=3840&q=75",
      "alt": "Balandosa"
    },
    {
      "id": 12,
      "image": "https://www.menutiger.com/_next/image?url=%2F_next%2Fstatic%2Fmedia%2Fpartner_4.3229abf4.webp&w=2048&q=75",
      "alt": "One Bite"
    },
    {
      "id": 13,
      "image": "https://www.menutiger.com/_next/image?url=%2F_next%2Fstatic%2Fmedia%2Fpartner_4.3229abf4.webp&w=2048&q=75",
      "alt": "Sagar Ratna"
    },
    {
      "id": 14,
      "image": "https://www.menutiger.com/_next/image?url=%2F_next%2Fstatic%2Fmedia%2Fpartner_4.3229abf4.webp&w=2048&q=75",
      "alt": "Shree Rathnam"
    },
    {
      "id": 15,
      "image": "https://www.menutiger.com/_next/image?url=%2F_next%2Fstatic%2Fmedia%2Fpartner_4.3229abf4.webp&w=2048&q=75",
      "alt": "South Indian"
    },
    {
      "id": 16,
      "image": "https://www.menutiger.com/_next/image?url=%2F_next%2Fstatic%2Fmedia%2Fpartner_4.3229abf4.webp&w=2048&q=75",
      "alt": "Swagath"
    },
    {
      "id": 17,
      "image": "https://www.menutiger.com/_next/image?url=%2F_next%2Fstatic%2Fmedia%2Fpartner_4.3229abf4.webp&w=2048&q=75",
      "alt": "Tunday Kababi"
    }
  ]
  